time_study_preprocessing_main/__init__.py
time_study_preprocessing_main/_version.py
time_study_preprocessing_main/preprocessing_all_ema.py
time_study_preprocessing_main/preprocessing_all_uema.py
time_study_preprocessing_main/preprocess_scripts/__init__.py
time_study_preprocessing_main/preprocess_scripts/phone/__init__.py
time_study_preprocessing_main/preprocess_scripts/phone/GPS/__init__.py
time_study_preprocessing_main/preprocess_scripts/phone/GPS/location_cluster_day.py
time_study_preprocessing_main/preprocess_scripts/phone/GPS/location_cluster_hour.py
time_study_preprocessing_main/preprocess_scripts/phone/GPS/location_cluster_minute.py
time_study_preprocessing_main/preprocess_scripts/phone/GPS/main.py
time_study_preprocessing_main/preprocess_scripts/phone/GPS/parse.py
time_study_preprocessing_main/preprocess_scripts/phone/ambient_press_sensor/__init__.py
time_study_preprocessing_main/preprocess_scripts/phone/ambient_press_sensor/main.py
time_study_preprocessing_main/preprocess_scripts/phone/ambient_press_sensor/parse.py
time_study_preprocessing_main/preprocess_scripts/phone/app_usage/__init__.py
time_study_preprocessing_main/preprocess_scripts/phone/app_usage/main.py
time_study_preprocessing_main/preprocess_scripts/phone/app_usage/parse.py
time_study_preprocessing_main/preprocess_scripts/phone/app_use_duration/__init__.py
time_study_preprocessing_main/preprocess_scripts/phone/app_use_duration/main.py
time_study_preprocessing_main/preprocess_scripts/phone/app_use_duration/parse.py
time_study_preprocessing_main/preprocess_scripts/phone/apps_installed/__init__.py
time_study_preprocessing_main/preprocess_scripts/phone/apps_installed/main.py
time_study_preprocessing_main/preprocess_scripts/phone/apps_installed/parse.py
time_study_preprocessing_main/preprocess_scripts/phone/battery/__init__.py
time_study_preprocessing_main/preprocess_scripts/phone/battery/battery_day.py
time_study_preprocessing_main/preprocess_scripts/phone/battery/battery_hour.py
microt_preprocessing-0.1.91.dist-info/LICENSE.txt
microt_preprocessing-0.1.91.dist-info/METADATA
microt_preprocessing-0.1.91.dist-info/WHEEL
microt_preprocessing-0.1.91.dist-info/top_level.txt
microt_preprocessing-0.1.91.dist-info/RECORD
